guard_post/.DS_Store
guard_post/__init__.py
guard_post/api/__init__.py
guard_post/api/assigns/__init__.py
guard_post/api/assigns/assign_edge_api_assigns_add_post.py
guard_post/api/assigns/check_relationship_api_assigns_check_post.py
guard_post/api/assigns/expand_relationship_api_assigns_expand_post.py
guard_post/api/assigns/list_edges_api_assigns_list_post.py
guard_post/api/assigns/revoke_user_to_org_api_assigns_revoke_post.py
guard_post/api/azure_ad/__init__.py
guard_post/api/azure_ad/get_user_api_active_dir_get_user_get.py
guard_post/api/azure_ad/signon_api_active_dir_signon_post.py
guard_post/api/orgs/__init__.py
guard_post/api/orgs/delete_api_orgs_delete_post.py
guard_post/api/orgs/list_items_api_orgs_list_get.py
guard_post/api/orgs/sync_api_orgs_sync_post.py
guard_post/api/ready/__init__.py
guard_post/api/ready/readiness_check_api_ready_get.py
guard_post/api/relations/__init__.py
guard_post/api/relations/list_objs_api_relations_list_objs_post.py
guard_post/api/relations/traverse_api_relations_traverse_post.py
guard_post/api/sites/__init__.py
guard_post/api/sites/delete_api_sites_delete_post.py
guard_post/api/sites/list_sites_api_sites_list_get.py
guard_post/api/sites/sync_api_sites_sync_post.py
guard_post/api/users/__init__.py
guard_post/api/users/delete_api_users_delete_post.py
guard_post/api/users/list_items_api_users_list_get.py
guard_post/api/users/sync_api_users_sync_post.py
guard_post/client.py
guard_post/core.py
guard_post/errors.py
guard_post/imports.py
guard_post/migrate/enums.py
guard_post/migrate/models.py
guard_post/models/__init__.py
guard_post/models/azure_user.py
guard_post/models/azure_user_acr_type_0.py
guard_post/models/azure_user_appidacr_type_0.py
guard_post/models/azure_user_azpacr_type_0.py
guard_post/models/azure_user_claims.py
guard_post/models/azure_user_ver.py
guard_post/models/create_org.py
guard_post/models/create_org_attributes.py
guard_post/models/create_org_key_type_0.py
guard_post/models/create_site.py
sc_guard_post-1.0.0.dist-info/METADATA
sc_guard_post-1.0.0.dist-info/WHEEL
sc_guard_post-1.0.0.dist-info/RECORD
